ApexUtils/DebuggingUtils.py
ApexUtils/IOUtils.py
ApexUtils/LMDBUtils.py
ApexUtils/LPIPSUtils.py
ApexUtils/MiscUtils.py
ApexUtils/NNUtils.py
ApexUtils/TensorManipulation.py
ApexUtils/__init__.py
apex_utils-0.0.7.dist-info/LICENSE
apex_utils-0.0.7.dist-info/METADATA
apex_utils-0.0.7.dist-info/WHEEL
apex_utils-0.0.7.dist-info/top_level.txt
apex_utils-0.0.7.dist-info/RECORD
