Metadata-Version: 2.1
Name: apex-utils
Version: 0.0.7
Summary: Useful utility functions for deep learning research
Author-email: Tristan Engst <tristanengst@gmail.com>
License: MIT License        
Project-URL: Homepage, https://github.com/tristanengst/apex-utils
Classifier: Programming Language :: Python :: 3
Classifier: License :: OSI Approved :: MIT License
Classifier: Operating System :: OS Independent
Requires-Python: >=3.7
License-File: LICENSE
